srp_nlp/__init__.py
srp_nlp/text_preprocessing.py
srp_nlp-0.1.dist-info/DESCRIPTION.rst
srp_nlp-0.1.dist-info/METADATA
srp_nlp-0.1.dist-info/RECORD
srp_nlp-0.1.dist-info/WHEEL
srp_nlp-0.1.dist-info/metadata.json
srp_nlp-0.1.dist-info/top_level.txt
