Metadata-Version: 2.0
Name: srp-nlp
Version: 0.1
Summary: Reusable NLP stuff in Python
Home-page: https://github.com/jwilber/srp_nlp
Author: Jared Wilber
Author-email: jdwlbr@gmail.com
License: GNU3
Platform: UNKNOWN
Requires-Dist: numpy
Requires-Dist: gensim
Requires-Dist: nltk
